main/__init__.py
main/cli.py
main/config.py
main/downloader.py
main/utils.py
tests/__init__.py
tests/test_cli.py
tests/test_download.py
ytb_download-1.2.0.dist-info/licenses/LICENSE
ytb_download-1.2.0.dist-info/METADATA
ytb_download-1.2.0.dist-info/WHEEL
ytb_download-1.2.0.dist-info/entry_points.txt
ytb_download-1.2.0.dist-info/top_level.txt
ytb_download-1.2.0.dist-info/RECORD
